zmung/__init__.py
zmung-1.0.dist-info/METADATA
zmung-1.0.dist-info/WHEEL
zmung-1.0.dist-info/top_level.txt
zmung-1.0.dist-info/RECORD
