Metadata-Version: 2.1
Name: zmung
Version: 1.0
Summary: python3 package to colors your output
Author-email: rootcli53@gmail.com
License: Eclipse Public License 2.0
